[
  {
    "id": "67901",
    "pic": "https://static.chemistwarehouse.com.au/ams/media/productimages/67901/original.jpg",
    "name": " Nature's Way Kids Smart Vita Gummies Immunity 60 Pastilles",
    "price": "8.99",
    "link": "/buy/67901/Nature-39-s-Way-Kids-Smart-Vita-Gummies-Immunity-60-Pastilles",
    "tags": [
      "nature's Way",
      "vitamin",
      "kids"
    ]
  },
  {
    "id": "62713",
    "pic": "https://static.chemistwarehouse.com.au/ams/media/productimages/62713/original.jpg",
    "name": " Nature's Way Kids Smart Vita Gummies Vitamin C 60 Gummies",
    "price": "8.99",
    "link": "/buy/62713/Nature-39-s-Way-Kids-Smart-Vita-Gummies-Vitamin-C-60-Gummies",
    "tags": [
      "nature's Way",
      "vitamin",
      "kids"
    ]
  },
  {
    "id": "64965",
    "pic": "https://static.chemistwarehouse.com.au/ams/media/productimages/64965/original.jpg",
    "name": " Nature's Way Kids Smart Vita Gummies Calcium 60 Pastilles",
    "price": "8.99",
    "link": "/buy/64965/Nature-39-s-Way-Kids-Smart-Vita-Gummies-Calcium-60-Pastilles",
    "tags": [
      "nature's Way",
      "vitamin",
      "kids"
    ]
  },
  {
    "id": "62714",
    "pic": "https://static.chemistwarehouse.com.au/ams/media/productimages/62714/original.jpg",
    "name": " Nature's Way Kids Smart Vita Gummies Multi Vitamin & Vegies 60 Gummies",
    "price": "8.99",
    "link": "/buy/62714/Nature-39-s-Way-Kids-Smart-Vita-Gummies-Multi-Vitamin-amp-Vegies-60-Gummies",
    "tags": [
      "nature's Way",
      "vitamin",
      "kids"
    ]
  },
  {
    "id": "62712",
    "pic": "https://static.chemistwarehouse.com.au/ams/media/productimages/62712/original.jpg",
    "name": " Nature's Way Kids Smart Vita Gummies Omega 3 Fish Oil 60",
    "price": "8.99",
    "link": "/buy/62712/Nature-39-s-Way-Kids-Smart-Vita-Gummies-Omega-3-Fish-Oil-60",
    "tags": [
      "nature's Way",
      "vitamin",
      "kids"
    ]
  },
  {
    "id": "66542",
    "pic": "https://static.chemistwarehouse.com.au/ams/media/productimages/66542/original.jpg",
    "name": " Nature's Way Kids Probiotic Balls 50",
    "price": "13.99",
    "link": "/buy/66542/Nature-39-s-Way-Kids-Probiotic-Balls-50",
    "tags": [
      "nature's Way",
      "vitamin",
      "kids"
    ]
  },
  {
    "id": "50074",
    "pic": "https://static.chemistwarehouse.com.au/ams/media/productimages/50074/original.jpg",
    "name": " Nature's Way Kids Smart Omega-3 Fish Oil Fruity Chewable Burstlets 50",
    "price": "13.99",
    "link": "/buy/50074/Nature-39-s-Way-Kids-Smart-Omega-3-Fish-Oil-Fruity-Chewable-Burstlets-50",
    "tags": [
      "nature's Way",
      "vitamin",
      "kids"
    ]
  },
  {
    "id": "52588",
    "pic": "https://static.chemistwarehouse.com.au/ams/media/productimages/52588/original.jpg",
    "name": " Nature's Way Kids Calcium Strawberry Milkshake Burstlets 50",
    "price": "13.99",
    "link": "/buy/52588/Nature-39-s-Way-Kids-Calcium-Strawberry-Milkshake-Burstlets-50",
    "tags": [
      "nature's Way",
      "vitamin",
      "kids"
    ]
  },
  {
    "id": "57246",
    "pic": "https://static.chemistwarehouse.com.au/ams/media/productimages/57246/original.jpg",
    "name": " Nature's Way Kids Smart Complete Multi Vitamin & Fish Oil 50 Capsules",
    "price": "14.69",
    "link": "/buy/57246/Nature-39-s-Way-Kids-Smart-Complete-Multi-Vitamin-amp-Fish-Oil-50-Capsules",
    "tags": [
      "nature's Way",
      "vitamin",
      "kids"
    ]
  },
  {
    "id": "59657",
    "pic": "https://static.chemistwarehouse.com.au/ams/media/productimages/59657/original.jpg",
    "name": " Nature's Way Kids Smart Omega 3 Fish Oil Trio 180 Capsules",
    "price": "34.69",
    "link": "/buy/59657/Nature-39-s-Way-Kids-Smart-Omega-3-Fish-Oil-Trio-180-Capsules",
    "tags": [
      "nature's Way",
      "vitamin",
      "kids"
    ]
  },
  {
    "id": "64966",
    "pic": "https://static.chemistwarehouse.com.au/ams/media/productimages/64966/original.jpg",
    "name": " Nature's Way Kids Smart Vita Gummies Multi Vitamin for Fussy Eaters 60 Pastilles",
    "price": "8.99",
    "link": "/buy/64966/Nature-39-s-Way-Kids-Smart-Vita-Gummies-Multi-Vitamin-for-Fussy-Eaters-60-Pastilles",
    "tags": [
      "nature's Way",
      "vitamin",
      "kids"
    ]
  },
  {
    "id": "80266",
    "pic": "https://static.chemistwarehouse.com.au/ams/media/productimages/80266/original.jpg",
    "name": " Nature's Way Kids Smart Drops DHA 20ml",
    "price": "9.99",
    "link": "/buy/80266/Nature-39-s-Way-Kids-Smart-Drops-DHA-20ml",
    "tags": [
      "nature's Way",
      "vitamin",
      "kids"
    ]
  },
  {
    "id": "71325",
    "pic": "https://static.chemistwarehouse.com.au/ams/media/productimages/71325/original.jpg",
    "name": " Nature's Way Kids Smart Vita Gummies Multi + Omega 50 Pastilles",
    "price": "8.99",
    "link": "/buy/71325/Nature-39-s-Way-Kids-Smart-Vita-Gummies-Multi-Omega-50-Pastilles",
    "tags": [
      "nature's Way",
      "vitamin",
      "kids"
    ]
  },
  {
    "id": "56442",
    "pic": "https://static.chemistwarehouse.com.au/ams/media/productimages/56442/original.jpg",
    "name": " Nature's Way Kids Smart Omega 3 Fish Oil Strawberry 50 Capsules",
    "price": "13.99",
    "link": "/buy/56442/Nature-39-s-Way-Kids-Smart-Omega-3-Fish-Oil-Strawberry-50-Capsules",
    "tags": [
      "nature's Way",
      "vitamin",
      "kids"
    ]
  },
  {
    "id": "62967",
    "pic": "https://static.chemistwarehouse.com.au/ams/media/productimages/62967/original.jpg",
    "name": " Nature's Way Kids Smart Complete Multi Vitamin & Fish Oil 100 Capsules",
    "price": "26.99",
    "link": "/buy/62967/Nature-39-s-Way-Kids-Smart-Complete-Multi-Vitamin-amp-Fish-Oil-100-Capsules",
    "tags": [
      "nature's Way",
      "vitamin",
      "kids"
    ]
  },
  {
    "id": "80269",
    "pic": "https://static.chemistwarehouse.com.au/ams/media/productimages/80269/original.jpg",
    "name": " Nature's Way Kids Smart Milk Buttons with DHA Vanilla 150 Chewable Buttons",
    "price": "9.99",
    "link": "/buy/80269/Nature-39-s-Way-Kids-Smart-Milk-Buttons-with-DHA-Vanilla-150-Chewable-Buttons",
    "tags": [
      "nature's Way",
      "vitamin",
      "kids"
    ]
  },
  {
    "id": "80271",
    "pic": "https://static.chemistwarehouse.com.au/ams/media/productimages/80271/original.jpg",
    "name": " Nature's Way Kids Smart Milk Buttons with Manuka Honey 150 Chewable Buttons",
    "price": "9.99",
    "link": "/buy/80271/Nature-39-s-Way-Kids-Smart-Milk-Buttons-with-Manuka-Honey-150-Chewable-Buttons",
    "tags": [
      "nature's Way",
      "vitamin",
      "kids"
    ]
  },
  {
    "id": "80487",
    "pic": "https://static.chemistwarehouse.com.au/ams/media/productimages/80487/original.jpg",
    "name": " Nature's Way Kids Smart Vita Gummies Fussy Eaters 150 Pastilles Exclusive Size",
    "price": "17.99",
    "link": "/buy/80487/Nature-39-s-Way-Kids-Smart-Vita-Gummies-Fussy-Eaters-150-Pastilles-Exclusive-Size",
    "tags": [
      "nature's Way",
      "vitamin",
      "kids"
    ]
  },
  {
    "id": "77890",
    "pic": "https://static.chemistwarehouse.com.au/ams/media/productimages/77890/original.jpg",
    "name": " Nature's Way Kids Smart Yoghurt Balls 50s",
    "price": "13.99",
    "link": "/buy/77890/Nature-39-s-Way-Kids-Smart-Yoghurt-Balls-50s",
    "tags": [
      "nature's Way",
      "vitamin",
      "kids"
    ]
  },
  {
    "id": "80270",
    "pic": "https://static.chemistwarehouse.com.au/ams/media/productimages/80270/original.jpg",
    "name": " Nature's Way Kids Smart Milk Buttons with Probiotics 150 Chewable Buttons",
    "price": "9.99",
    "link": "/buy/80270/Nature-39-s-Way-Kids-Smart-Milk-Buttons-with-Probiotics-150-Chewable-Buttons",
    "tags": [
      "nature's Way",
      "vitamin",
      "kids"
    ]
  },
  {
    "id": "80267",
    "pic": "https://static.chemistwarehouse.com.au/ams/media/productimages/80267/original.jpg",
    "name": " Nature's Way Kids Smart Drops Probiotic 20ml",
    "price": "12.99",
    "link": "/buy/80267/Nature-39-s-Way-Kids-Smart-Drops-Probiotic-20ml",
    "tags": [
      "nature's Way",
      "vitamin",
      "kids"
    ]
  },
  {
    "id": "80268",
    "pic": "https://static.chemistwarehouse.com.au/ams/media/productimages/80268/original.jpg",
    "name": " Nature's Way Kids Smart Drops Vitamin D 20ml",
    "price": "6.99",
    "link": "/buy/80268/Nature-39-s-Way-Kids-Smart-Drops-Vitamin-D-20ml",
    "tags": [
      "nature's Way",
      "vitamin",
      "kids"
    ]
  },
  {
    "id": "75450",
    "pic": "https://static.chemistwarehouse.com.au/ams/media/productimages/75450/original.jpg",
    "name": " Nature's Way Kids Restore Probiotic 30 Tablets",
    "price": "10.00",
    "link": "/buy/75450/Nature-39-s-Way-Kids-Restore-Probiotic-30-Tablets",
    "tags": [
      "nature's Way",
      "vitamin",
      "kids"
    ]
  },
  {
    "id": "75451",
    "pic": "https://static.chemistwarehouse.com.au/ams/media/productimages/75451/original.jpg",
    "name": " Nature's Way Kids Probiotic Powder 50g",
    "price": "15.00",
    "link": "/buy/75451/Nature-39-s-Way-Kids-Probiotic-Powder-50g",
    "tags": [
      "nature's Way",
      "vitamin",
      "kids"
    ]
  },
  {
    "id": "80272",
    "pic": "https://static.chemistwarehouse.com.au/ams/media/productimages/80272/original.jpg",
    "name": " Nature's Way Kids Smart Triple Strength DHA 300mg 50 Soft Capsules",
    "price": "15.99",
    "link": "/buy/80272/Nature-39-s-Way-Kids-Smart-Triple-Strength-DHA-300mg-50-Soft-Capsules",
    "tags": [
      "nature's Way",
      "vitamin",
      "kids"
    ]
  }
]
